{
    "version": 1,
    "all_bricks": {
        "300": {
            "submit_time": [
                1682169261
            ],
            "type": 2
        },
        "1064": {
            "submit_time": [
                1683709849,
                1683709869,
                1683709959
            ],
            "type": 2
        },
        "1065": {
            "submit_time": [
                1683772902
            ],
            "type": 2
        },
        "1096": {
            "submit_time": [
                1682565068
            ],
            "type": 2
        },
        "1121": {
            "submit_time": [
                1681906415,
                1681906504
            ],
            "type": 2
        },
        "1129": {
            "submit_time": [
                1682603486
            ],
            "type": 2
        },
        "1196": {
            "submit_time": [
                1682238934
            ],
            "type": 2
        },
        "2229": {
            "submit_time": [
                1683199901
            ],
            "type": 2
        },
        "2502": {
            "submit_time": [
                1682406498,
                1682407349
            ],
            "type": 2
        },
        "2518": {
            "submit_time": [
                1683282966
            ],
            "type": 2
        },
        "2532": {
            "submit_time": [
                1682779985
            ],
            "type": 2
        },
        "2547": {
            "submit_time": [
                1684981728
            ],
            "type": 2
        },
        "2566": {
            "submit_time": [
                1686631173
            ],
            "type": 2
        }
    }
}